spg120.py
spg120-0.2.2.dist-info/licenses/LICENSE
spg120-0.2.2.dist-info/METADATA
spg120-0.2.2.dist-info/WHEEL
spg120-0.2.2.dist-info/top_level.txt
spg120-0.2.2.dist-info/RECORD
