Metadata-Version: 2.4
Name: spg120
Version: 0.2.2
Summary: Python interface for Spectrometer SPG 120 by Shimadzu
Author-email: Akira Okumura <oxon@mac.com>
License: MIT License
Project-URL: Repository, https://github.com/akira-okumura/spg120.git
Project-URL: Issues, https://github.com/akira-okumura/spg120/issues
Classifier: Programming Language :: Python :: 3
Classifier: License :: OSI Approved :: MIT License
Classifier: Operating System :: OS Independent
License-File: LICENSE
Requires-Dist: pysigmakoki>=2.1.7
Dynamic: license-file
